LICENSE
MANIFEST.in
README.md
settings.ini
setup.py
pregi/__init__.py
pregi/_modidx.py
pregi/core.py
pregi.egg-info/PKG-INFO
pregi.egg-info/SOURCES.txt
pregi.egg-info/dependency_links.txt
pregi.egg-info/entry_points.txt
pregi.egg-info/not-zip-safe
pregi.egg-info/requires.txt
pregi.egg-info/top_level.txt