Metadata-Version: 2.1
Name: pregi
Version: 0.0.0
Summary: Prediction of genetic interactors
Home-page: https://github.com/rraadd88/pregi/
Author: Rohan Dandage
Author-email: rohanadandage@gmail.com
License: Apache Software License 2.0
Keywords: CRISPR,Genetic interactions,Synthetic lethality
Classifier: Development Status :: 3 - Alpha
Classifier: Intended Audience :: Developers
Classifier: Natural Language :: English
Classifier: Programming Language :: Python :: 3.7
Classifier: Programming Language :: Python :: 3.8
Classifier: Programming Language :: Python :: 3.9
Classifier: Programming Language :: Python :: 3.10
Classifier: License :: OSI Approved :: Apache Software License
Requires-Python: >=3.7
License-File: LICENSE
Provides-Extra: dev
